bean_sort.py
bean_sort-0.1.1.dist-info/entry_points.txt
bean_sort-0.1.1.dist-info/licenses/COPYING
bean_sort-0.1.1.dist-info/WHEEL
bean_sort-0.1.1.dist-info/METADATA
bean_sort-0.1.1.dist-info/RECORD
