Metadata-Version: 2.4
Name: bean-sort
Version: 0.1.1
Summary: Naive sorting for Beancount files
Keywords: beancount
Requires-Python: >=3.11
License-Expression: GPL-3.0-or-later
Classifier: Development Status :: 4 - Beta
Classifier: Environment :: Console
Classifier: Intended Audience :: End Users/Desktop
Classifier: Topic :: Utilities
Classifier: Programming Language :: Python :: 3
Classifier: Programming Language :: Python :: 3.11
License-File: COPYING
Project-URL: Homepage, https://github.com/tesujimath/bean-sort
Project-URL: Repository, https://github.com/tesujimath/bean-sort
